findpy/__init__.py
findpy/find.py
findpy-0.1.dist-info/LICENSE
findpy-0.1.dist-info/METADATA
findpy-0.1.dist-info/WHEEL
findpy-0.1.dist-info/top_level.txt
findpy-0.1.dist-info/RECORD
