Metadata-Version: 2.1
Name: findpy
Version: 0.1
Summary: Find folders and files, find string in files, txt, etc..
Home-page: https://github.com/MayconFelipeA/findpy
Author: Maycon Felipe
Author-email: maycon_felipegato@hotmail.com
License: UNKNOWN
Keywords: Findpy findString findFolder find archives
Platform: UNKNOWN
Classifier: License :: OSI Approved :: MIT License
Classifier: Operating System :: OS Independent
Classifier: Programming Language :: Python :: 3.6
Classifier: Programming Language :: Python :: 3.8
Requires-Python: >=3.6
